funcy_pipe/__init__.py
funcy_pipe/__init__.pyi
funcy_pipe/chain.py
funcy_pipe/funcy_extensions.py
funcy_pipe/macro.py
funcy_pipe/pipe.py
funcy_pipe-0.14.0.dist-info/LICENSE
funcy_pipe-0.14.0.dist-info/METADATA
funcy_pipe-0.14.0.dist-info/WHEEL
funcy_pipe-0.14.0.dist-info/RECORD
