Metadata-Version: 2.1
Name: funcy-pipe
Version: 0.14.0
Summary: If Funcy and Pipe had a baby. Decorates all Funcy methods with Pipe superpowers.
Home-page: https://github.com/iloveitaly/funcy-pipe
License: MIT
Keywords: python,functional-programming,pipe,funcy,data-manipulation
Author: Michael Bianco
Author-email: mike@mikebian.co
Requires-Python: >=3.8,<4.0
Classifier: License :: OSI Approved :: MIT License
Classifier: Programming Language :: Python :: 3
Classifier: Programming Language :: Python :: 3.8
Classifier: Programming Language :: Python :: 3.9
Classifier: Programming Language :: Python :: 3.10
Classifier: Programming Language :: Python :: 3.11
Classifier: Programming Language :: Python :: 3.12
Requires-Dist: funcy (>=2.0,<3.0)
